gsheetread/__init__.py
gsheetread/config.py
gsheetread/read.py
gsheetread-0.1.2.dist-info/WHEEL
gsheetread-0.1.2.dist-info/METADATA
gsheetread-0.1.2.dist-info/RECORD
